<?xml version="1.0" encoding="utf-8"?>
<Items>
  <Override>
    <Item name="Empty Rum Bottle" identifier="he-emptybottlerum" category="Misc,Material,Ingredient" maxstacksize="8" cargocontaineridentifier="metalcrate" description="An empty rum bottle. Can be thrown or used in water to collect dirty water." Tags="smallitem,ingredient" useinhealthinterface="false" scale="0.5" impactsoundtag="impact_metal_light" impacttolerance="5.5" isshootable="true" requireaimtouse="true">
      <Sprite texture="%ModDir:2532991202%/Integrations/Hungry Europans/Content/Items/Food/DrinksAndIngredients.png" sourcerect="27,0,27,66" depth="0.499" origin="0.5,0.5" />
      <Body width="27" height="66" density="8" />
      <Deconstruct time="0.5" />
      <Throwable characterusable="true" canBeCombined="false" slots="Any,RightHand,LeftHand" throwforce="4.0" aimpos="35,-10" msg="ItemMsgPickUpSelect">
        <StatusEffect type="OnUse" target="This">
          <Conditional InWater="true" />
          <Sound file="Content/Sounds/Water/Splash0.ogg" range="200" volume="0.5" />
          <Remove />
          <SpawnItem identifier="he-seawaterrum" spawnposition="SameInventory" spawnifcantbecontained="true" />
        </StatusEffect>
        <StatusEffect type="OnImpact" target="This" Condition="0.0" setvalue="true">
          <ParticleEmitter particle="whitegoosplash" anglemin="0" anglemax="360" particleamount="2" velocitymin="0" velocitymax="0" scalemin="0.5" scalemax="1" />
          <Sound file="Content/Sounds/Damage/GlassImpact1.ogg" selectionmode="Random" range="600" />
          <Sound file="Content/Sounds/Damage/GlassImpact2.ogg" selectionmode="Random" range="600" />
          <Sound file="Content/Sounds/Damage/GlassImpact3.ogg" selectionmode="Random" range="600" />
          <Sound file="Content/Sounds/Damage/GlassImpact4.ogg" selectionmode="Random" range="600" />
          <Remove />
        </StatusEffect>
      </Throwable>
    </Item>
    <Item name="Empty Whiskey Bottle" identifier="he-emptybottlewhiskey" category="Misc,Material,Ingredient" maxstacksize="8" cargocontaineridentifier="metalcrate" description="An empty Whiskey bottle. Can be thrown or used in water to collect dirty water." Tags="smallitem,ingredient" useinhealthinterface="false" scale="0.5" impactsoundtag="impact_metal_light" impacttolerance="5.5" isshootable="true" requireaimtouse="true">
      <Sprite texture="%ModDir:2532991202%/Integrations/Hungry Europans/Content/Items/Food/DrinksAndIngredients.png" sourcerect="110,0,27,66" depth="0.499" origin="0.5,0.5" />
      <Body width="27" height="66" density="8" />
      <Deconstruct time="0.5" />
      <Throwable characterusable="true" canBeCombined="false" slots="Any,RightHand,LeftHand" throwforce="4.0" aimpos="35,-10" msg="ItemMsgPickUpSelect">
        <StatusEffect type="OnUse" target="This">
          <Conditional InWater="true" />
          <Sound file="Content/Sounds/Water/Splash0.ogg" range="200" volume="0.5" />
          <Remove />
          <SpawnItem identifier="he-seawaterwhiskey" spawnposition="SameInventory" spawnifcantbecontained="true" />
        </StatusEffect>
        <StatusEffect type="OnImpact" target="This" Condition="0.0" setvalue="true">
          <ParticleEmitter particle="whitegoosplash" anglemin="0" anglemax="360" particleamount="2" velocitymin="0" velocitymax="0" scalemin="0.5" scalemax="1" />
          <Sound file="Content/Sounds/Damage/GlassImpact1.ogg" selectionmode="Random" range="600" />
          <Sound file="Content/Sounds/Damage/GlassImpact2.ogg" selectionmode="Random" range="600" />
          <Sound file="Content/Sounds/Damage/GlassImpact3.ogg" selectionmode="Random" range="600" />
          <Sound file="Content/Sounds/Damage/GlassImpact4.ogg" selectionmode="Random" range="600" />
          <Remove />
        </StatusEffect>
      </Throwable>
    </Item>
    <Item name="Empty Halucinova Bottle" identifier="he-emptybottlehalucinova" category="Misc,Material,Ingredient" maxstacksize="8" cargocontaineridentifier="metalcrate" description="An empty Halucinova bottle. Can be thrown or used in water to collect dirty water." Tags="smallitem,ingredient" useinhealthinterface="false" scale="0.5" impactsoundtag="impact_metal_light" impacttolerance="5.5" isshootable="true" requireaimtouse="true">
      <Sprite texture="%ModDir:2532991202%/Integrations/Hungry Europans/Content/Items/Food/DrinksAndIngredients.png" sourcerect="425,2,31,64" depth="0.499" origin="0.5,0.5" />
      <Body width="27" height="66" density="8" />
      <Deconstruct time="0.5" />
      <Throwable characterusable="true" canBeCombined="false" slots="Any,RightHand,LeftHand" throwforce="4.0" aimpos="35,-10" msg="ItemMsgPickUpSelect">
        <StatusEffect type="OnUse" target="This">
          <Conditional InWater="true" />
          <Sound file="Content/Sounds/Water/Splash0.ogg" range="200" volume="0.5" />
          <Remove />
          <SpawnItem identifier="he-seawaterhalucinova" spawnposition="SameInventory" spawnifcantbecontained="true" />
        </StatusEffect>
        <StatusEffect type="OnImpact" target="This" Condition="0.0" setvalue="true">
          <ParticleEmitter particle="whitegoosplash" anglemin="0" anglemax="360" particleamount="2" velocitymin="0" velocitymax="0" scalemin="0.5" scalemax="1" />
          <Sound file="Content/Sounds/Damage/GlassImpact1.ogg" selectionmode="Random" range="600" />
          <Sound file="Content/Sounds/Damage/GlassImpact2.ogg" selectionmode="Random" range="600" />
          <Sound file="Content/Sounds/Damage/GlassImpact3.ogg" selectionmode="Random" range="600" />
          <Sound file="Content/Sounds/Damage/GlassImpact4.ogg" selectionmode="Random" range="600" />
          <Remove />
        </StatusEffect>
      </Throwable>
    </Item>
    <Item name="Empty Bottle" identifier="he-emptybottle" category="Misc,Material,Ingredient" maxstacksize="8" cargocontaineridentifier="metalcrate" description="An empty bottle. Can be thrown or used in water to collect dirty water." Tags="smallitem,ingredient" useinhealthinterface="false" scale="0.5" impactsoundtag="impact_metal_light" impacttolerance="5.5" isshootable="true" requireaimtouse="true">
      <Sprite texture="%ModDir:2532991202%/Integrations/Hungry Europans/Content/Items/Food/DrinksAndIngredients.png" sourcerect="180,8,21,58" depth="0.499" origin="0.5,0.5" />
      <Body width="21" height="58" density="8" />
      <Deconstruct time="0.5" />
      <Throwable characterusable="true" canBeCombined="false" slots="Any,RightHand,LeftHand" throwforce="4.0" aimpos="35,-10" msg="ItemMsgPickUpSelect">
        <StatusEffect type="OnUse" target="This">
          <Conditional InWater="true" />
          <Sound file="Content/Sounds/Water/Splash0.ogg" range="200" volume="0.5" />
          <Remove />
          <SpawnItem identifier="he-seawater" spawnposition="SameInventory" spawnifcantbecontained="true" />
        </StatusEffect>
        <StatusEffect type="OnImpact" target="This" Condition="0.0" setvalue="true">
          <ParticleEmitter particle="whitegoosplash" anglemin="0" anglemax="360" particleamount="2" velocitymin="0" velocitymax="0" scalemin="0.5" scalemax="1" />
          <Sound file="Content/Sounds/Damage/GlassImpact1.ogg" selectionmode="Random" range="600" />
          <Sound file="Content/Sounds/Damage/GlassImpact2.ogg" selectionmode="Random" range="600" />
          <Sound file="Content/Sounds/Damage/GlassImpact3.ogg" selectionmode="Random" range="600" />
          <Sound file="Content/Sounds/Damage/GlassImpact4.ogg" selectionmode="Random" range="600" />
          <Remove />
        </StatusEffect>
      </Throwable>
    </Item>
    <Item name="Empty Beer Bottle" identifier="he-emptybottlebeer" category="Misc,Material,Ingredient" maxstacksize="1" cargocontaineridentifier="metalcrate" description="An empty beer bottle. Can be thrown or used in water to collect dirty water." Tags="smallitem,ingredient,emptybottle" useinhealthinterface="false" scale="0.5" impactsoundtag="impact_metal_light" impacttolerance="5.5" isshootable="true" requireaimtouse="true">
      <PreferredContainer secondary="wreckmedcab,abandonedmedcab" amount="1" spawnprobability="0.01" />
      <PreferredContainer secondary="abandonedcrewcab" minamount="1" maxamount="1" spawnprobability="0.01" />
      <PreferredContainer secondary="crewcab" amount="1" spawnprobability="0.02" notcampaign="true" />
      <PreferredContainer primary="kitchen" secondary="crewcab" />
      <Sprite texture="%ModDir:2532991202%/Integrations/Hungry Europans/Content/Items/Food/DrinksAndIngredients.png" sourcerect="494,1,17,65" depth="0.499" origin="0.5,0.5" />
      <InventoryIcon texture="%ModDir:2532991202%/Integrations/Hungry Europans/Content/Items/Food/DrinksAndIngredients.png" sourcerect="494,1,17,65" origin="0.5,0.5" />
      <ContainedSprite allowedcontainertags="refillstation" texture="%ModDir:2532991202%/Integrations/Hungry Europans/Content/Items/Food/DrinksAndIngredients.png" sourcerect="0,0,1,1" depth="0.55" origin="0.5,0.5" />
      <Body width="17" height="63" density="8" />
      <Deconstruct time="0.5" />
      <Throwable characterusable="true" canBeCombined="false" slots="Any,RightHand,LeftHand" throwforce="4.0" aimpos="35,-10" msg="ItemMsgPickUpSelect">
        <StatusEffect type="OnUse" target="This" interval="0.1">
          <Conditional InWater="true" />
          <Sound file="Content/Sounds/Water/Splash0.ogg" range="200" volume="0.5" />
          <Remove />
          <SpawnItem identifier="he-seawaterbeer" spawnposition="SameInventory" spawnifcantbecontained="true" SpawnIfInventoryFull="true" />
        </StatusEffect>
        <StatusEffect type="OnImpact" target="This" Condition="0.0" setvalue="true">
          <ParticleEmitter particle="whitegoosplash" anglemin="0" anglemax="360" particleamount="2" velocitymin="0" velocitymax="0" scalemin="0.5" scalemax="1" />
          <Sound file="Content/Sounds/Damage/GlassImpact1.ogg" selectionmode="Random" range="600" />
          <Sound file="Content/Sounds/Damage/GlassImpact2.ogg" selectionmode="Random" range="600" />
          <Sound file="Content/Sounds/Damage/GlassImpact3.ogg" selectionmode="Random" range="600" />
          <Sound file="Content/Sounds/Damage/GlassImpact4.ogg" selectionmode="Random" range="600" />
          <Remove />
        </StatusEffect>
      </Throwable>
    </Item>
    <!-- MEATS USED AS DECORATION IN BUTCHERSHOP  -->
    <!--crawler-->
    <Item name="Crawler Half" identifier="he-crawlermeatchunk" category="Misc,Material,Ingredient" maxstacksize="8" cargocontaineridentifier="he-coolercrate" description="" Tags="smallitem,meat,ingredient,canspoil,petfood1,petfood2,petfood3" useinhealthinterface="false" scale="0.5" impactsoundtag="impact_soft" isshootable="true" requireaimtouse="true">
      <Sprite texture="%ModDir:2532991202%/Integrations/Hungry Europans/Content/Items/Food/FoodAndMeat.png" sourcerect="311,446,200,66" depth="0.6" origin="0.5,0.5" />
      <Body width="200" radius="33" density="12" />
      <AiTarget sightrange="1000" static="True" />
    </Item>
    <Item name="Raw Crawler Meat" identifier="he-rawcrawlermeat" category="Misc,Material,Ingredient" maxstacksize="8" cargocontaineridentifier="he-coolercrate" description="" Tags="smallitem,meat,ingredient,canspoil,petfood1,petfood2,petfood3" useinhealthinterface="false" scale="0.5" impactsoundtag="impact_soft" isshootable="true" requireaimtouse="true">
      <Sprite texture="%ModDir:2532991202%/Integrations/Hungry Europans/Content/Items/Food/FoodAndMeat.png" sourcerect="258,477,51,17" depth="0.6" origin="0.5,0.5" />
      <Body width="51" radius="8" density="9" />
      <AiTarget sightrange="1000" static="True" />
    </Item>
    <Item name="Raw Crawler Meat Patty" identifier="he-rawcrawlermeatpatty" category="Misc,Material,Ingredient" maxstacksize="8" cargocontaineridentifier="he-coolercrate" description="" Tags="smallitem,meat,ingredient,canspoil,petfood1,petfood2,petfood3" useinhealthinterface="false" scale="0.5" impactsoundtag="impact_soft" isshootable="true" requireaimtouse="true">
      <Sprite texture="%ModDir:2532991202%/Integrations/Hungry Europans/Content/Items/Food/FoodAndMeat.png" sourcerect="275,459,35,17" depth="0.6" origin="0.5,0.5" />
      <Body width="35" radius="7" density="9" />
      <AiTarget sightrange="1000" static="True" />
    </Item>
    <Item name="Raw Crawler Sausage" identifier="he-rawcrawlersausage" category="Misc,Material,Ingredient" maxstacksize="8" cargocontaineridentifier="he-coolercrate" description="" Tags="smallitem,meat,ingredient,canspoil,petfood1,petfood2,petfood3" useinhealthinterface="false" scale="0.5" impactsoundtag="impact_soft" isshootable="true" requireaimtouse="true">
      <Sprite texture="%ModDir:2532991202%/Integrations/Hungry Europans/Content/Items/Food/FoodAndMeat.png" sourcerect="243,444,67,14" depth="0.6" origin="0.5,0.5" />
      <Body width="67" radius="7" density="9" />
      <AiTarget sightrange="1000" static="True" />
    </Item>
    <!--mudraptor-->
    <Item name="Mudraptor Meat Chunk" identifier="he-mudraptormeatchunk" category="Misc,Material,Ingredient" maxstacksize="8" cargocontaineridentifier="he-coolercrate" description="" Tags="smallitem,meat,ingredient,canspoil,petfood1,petfood2,petfood3" useinhealthinterface="false" scale="0.5" impactsoundtag="impact_soft" isshootable="true" requireaimtouse="true">
      <Sprite texture="%ModDir:2532991202%/Integrations/Hungry Europans/Content/Items/Food/FoodAndMeat.png" sourcerect="367,234,145,74" depth="0.6" origin="0.5,0.5" />
      <Body width="145" radius="37" density="12" />
      <AiTarget sightrange="1000" static="True" />
    </Item>
    <Item name="Raw Mudraptor Meat" identifier="he-rawmudraptormeat" category="Misc,Material,Ingredient" maxstacksize="8" cargocontaineridentifier="he-coolercrate" description="" Tags="smallitem,meat,ingredient,canspoil,petfood1,petfood2,petfood3" useinhealthinterface="false" scale="0.5" impactsoundtag="impact_soft" isshootable="true" requireaimtouse="true">
      <Sprite texture="%ModDir:2532991202%/Integrations/Hungry Europans/Content/Items/Food/FoodAndMeat.png" sourcerect="325,332,52,21" depth="0.6" origin="0.5,0.5" />
      <Body width="52" radius="10" density="12" />
      <AiTarget sightrange="1000" static="True" />
    </Item>
    <Item name="Raw Mudraptor Meat Patty" identifier="he-rawmudraptormeatpatty" category="Misc,Material,Ingredient" maxstacksize="8" cargocontaineridentifier="he-coolercrate" description="" Tags="smallitem,meat,ingredient,canspoil,petfood1,petfood2,petfood3" useinhealthinterface="false" scale="0.5" impactsoundtag="impact_soft" isshootable="true" requireaimtouse="true">
      <Sprite texture="%ModDir:2532991202%/Integrations/Hungry Europans/Content/Items/Food/FoodAndMeat.png" sourcerect="275,459,35,17" depth="0.6" origin="0.5,0.5" />
      <Body width="35" radius="7" density="9" />
      <AiTarget sightrange="1000" static="True" />
    </Item>
    <Item name="Raw Mudraptor Sausage" identifier="he-rawmudraptorsausage" category="Misc,Material,Ingredient" maxstacksize="8" cargocontaineridentifier="he-coolercrate" description="" Tags="smallitem,meat,ingredient,canspoil,petfood1,petfood2,petfood3" useinhealthinterface="false" scale="0.5" impactsoundtag="impact_soft" isshootable="true" requireaimtouse="true">
      <Sprite texture="%ModDir:2532991202%/Integrations/Hungry Europans/Content/Items/Food/FoodAndMeat.png" sourcerect="243,444,67,14" depth="0.6" origin="0.5,0.5" />
      <Body width="67" radius="7" density="9" />
      <AiTarget sightrange="1000" static="True" />
    </Item>
    <Item name="Raw Mudraptor Roast" identifier="he-rawmudraptorroast" category="Misc,Material,Ingredient" maxstacksize="8" cargocontaineridentifier="he-coolercrate" description="" Tags="smallitem,meat,ingredient,canspoil,petfood1,petfood2,petfood3" useinhealthinterface="false" scale="0.5" impactsoundtag="impact_soft" isshootable="true" requireaimtouse="true">
      <Sprite texture="%ModDir:2532991202%/Integrations/Hungry Europans/Content/Items/Food/FoodAndMeat.png" sourcerect="240,414,93,29" depth="0.6" origin="0.5,0.5" />
      <Body width="93" radius="14" density="12" />
      <AiTarget sightrange="1000" static="True" />
    </Item>
    <!--thresher-->
    <Item name="Thresher Meat Chunk" identifier="he-threshermeatchunk" category="Misc,Material,Ingredient" maxstacksize="8" cargocontaineridentifier="he-coolercrate" description="" Tags="smallitem,meat,ingredient,canspoil,petfood1,petfood2,petfood3" useinhealthinterface="false" scale="0.5" impactsoundtag="impact_soft" isshootable="true" requireaimtouse="true">
      <Sprite texture="%ModDir:2532991202%/Integrations/Hungry Europans/Content/Items/Food/FoodAndMeat.png" sourcerect="334,392,178,53" depth="0.6" origin="0.5,0.5" />
      <Body width="178" radius="26" density="15" />
      <AiTarget sightrange="1000" static="True" />
    </Item>
    <Item name="Raw Thresher Meat" identifier="he-rawthreshermeat" category="Misc,Material,Ingredient" maxstacksize="8" cargocontaineridentifier="he-coolercrate" description="" Tags="smallitem,meat,ingredient,canspoil,petfood1,petfood2,petfood3" useinhealthinterface="false" scale="0.5" impactsoundtag="impact_soft" isshootable="true" requireaimtouse="true">
      <Sprite texture="%ModDir:2532991202%/Integrations/Hungry Europans/Content/Items/Food/FoodAndMeat.png" sourcerect="258,477,51,17" depth="0.6" origin="0.5,0.5" />
      <Body width="51" radius="8" density="15" />
      <AiTarget sightrange="1000" static="True" />
    </Item>
    <Item name="Raw Thresher Meat Patty" identifier="he-rawthreshermeatpatty" category="Misc,Material,Ingredient" maxstacksize="8" cargocontaineridentifier="he-coolercrate" description="" Tags="smallitem,meat,ingredient,canspoil,petfood1,petfood2,petfood3" useinhealthinterface="false" scale="0.5" impactsoundtag="impact_soft" isshootable="true" requireaimtouse="true">
      <Sprite texture="%ModDir:2532991202%/Integrations/Hungry Europans/Content/Items/Food/FoodAndMeat.png" sourcerect="275,459,35,17" depth="0.6" origin="0.5,0.5" />
      <Body width="35" radius="7" density="9" />
      <AiTarget sightrange="1000" static="True" />
    </Item>
    <Item name="Raw Thresher Sausage" identifier="he-rawthreshersausage" category="Misc,Material,Ingredient" maxstacksize="8" cargocontaineridentifier="he-coolercrate" description="" Tags="smallitem,meat,ingredient,canspoil,petfood1,petfood2,petfood3" useinhealthinterface="false" scale="0.5" impactsoundtag="impact_soft" isshootable="true" requireaimtouse="true">
      <Sprite texture="%ModDir:2532991202%/Integrations/Hungry Europans/Content/Items/Food/FoodAndMeat.png" sourcerect="243,444,67,14" depth="0.6" origin="0.5,0.5" />
      <Body width="67" radius="7" density="9" />
      <AiTarget sightrange="1000" static="True" />
    </Item>
    <!--hammerhead-->
    <Item name="Hammerhead Spawn" identifier="he-hammerheadspawnmeatchunk" category="Misc,Material,Ingredient" maxstacksize="8" cargocontaineridentifier="he-coolercrate" description="" Tags="smallitem,meat,ingredient,canspoil,petfood1,petfood2,petfood3" useinhealthinterface="false" scale="0.5" impactsoundtag="impact_soft" isshootable="true" requireaimtouse="true">
      <Sprite texture="%ModDir:2532991202%/Integrations/Hungry Europans/Content/Items/Food/FoodAndMeat.png" sourcerect="431,309,81,34" depth="0.6" origin="0.5,0.5" />
      <Body width="81" radius="17" density="12" />
      <AiTarget sightrange="1000" static="True" />
    </Item>
    <Item name="Hammerhead Meat Chunk" identifier="he-hammerheadmeatchunk" category="Misc,Material,Ingredient" maxstacksize="8" cargocontaineridentifier="he-coolercrate" description="" Tags="smallitem,meat,ingredient,canspoil,petfood1,petfood2,petfood3" useinhealthinterface="false" scale="0.5" impactsoundtag="impact_soft" isshootable="true" requireaimtouse="true">
      <Sprite texture="%ModDir:2532991202%/Integrations/Hungry Europans/Content/Items/Food/FoodAndMeat.png" sourcerect="354,151,158,82" depth="0.6" origin="0.5,0.5" />
      <Body width="158" radius="41" density="12" />
      <AiTarget sightrange="1000" static="True" />
    </Item>
    <Item name="Raw Hammerhead Meat" identifier="he-rawhammerheadmeat" category="Misc,Material,Ingredient" maxstacksize="8" cargocontaineridentifier="he-coolercrate" description="" Tags="smallitem,meat,ingredient,canspoil,petfood1,petfood2,petfood3" useinhealthinterface="false" scale="0.5" impactsoundtag="impact_soft" isshootable="true" requireaimtouse="true">
      <Sprite texture="%ModDir:2532991202%/Integrations/Hungry Europans/Content/Items/Food/FoodAndMeat.png" sourcerect="327,354,50,25" depth="0.6" origin="0.5,0.5" />
      <Body width="50" radius="12" density="12" />
      <AiTarget sightrange="1000" static="True" />
    </Item>
    <Item name="Raw Hammerhead Meat Patty" identifier="he-rawhammerheadmeatpatty" category="Misc,Material,Ingredient" maxstacksize="8" cargocontaineridentifier="he-coolercrate" description="" Tags="smallitem,meat,ingredient,canspoil,petfood1,petfood2,petfood3" useinhealthinterface="false" scale="0.5" impactsoundtag="impact_soft" isshootable="true" requireaimtouse="true">
      <Sprite texture="%ModDir:2532991202%/Integrations/Hungry Europans/Content/Items/Food/FoodAndMeat.png" sourcerect="275,459,35,17" depth="0.6" origin="0.5,0.5" />
      <Body width="35" radius="7" density="9" />
      <AiTarget sightrange="1000" static="True" />
    </Item>
    <Item name="Raw Hammerhead Sausage" identifier="he-rawhammerheadsausage" category="Misc,Material,Ingredient" maxstacksize="8" cargocontaineridentifier="he-coolercrate" description="" Tags="smallitem,meat,ingredient,canspoil,petfood1,petfood2,petfood3" useinhealthinterface="false" scale="0.5" impactsoundtag="impact_soft" isshootable="true" requireaimtouse="true">
      <Sprite texture="%ModDir:2532991202%/Integrations/Hungry Europans/Content/Items/Food/FoodAndMeat.png" sourcerect="243,444,67,14" depth="0.6" origin="0.5,0.5" />
      <Body width="67" radius="7" density="9" />
      <AiTarget sightrange="1000" static="True" />
    </Item>
    <Item name="Raw Hammerhead Spareribs" identifier="he-rawhammerheadspareribs" category="Misc,Material,Ingredient" maxstacksize="8" cargocontaineridentifier="he-coolercrate" description="" Tags="smallitem,meat,ingredient,canspoil,petfood1,petfood2,petfood3" useinhealthinterface="false" scale="0.5" impactsoundtag="impact_soft" isshootable="true" requireaimtouse="true">
      <Sprite texture="%ModDir:2532991202%/Integrations/Hungry Europans/Content/Items/Food/FoodAndMeat.png" sourcerect="263,339,61,40" depth="0.6" origin="0.5,0.5" />
      <Body width="61" radius="18" density="12" />
      <AiTarget sightrange="1000" static="True" />
    </Item>
    <Item name="Raw Hammerhead Roast" identifier="he-rawhammerheadroast" category="Misc,Material,Ingredient" maxstacksize="8" cargocontaineridentifier="he-coolercrate" description="" Tags="smallitem,meat,ingredient,canspoil,petfood1,petfood2,petfood3" useinhealthinterface="false" scale="0.5" impactsoundtag="impact_soft" isshootable="true" requireaimtouse="true">
      <Sprite texture="%ModDir:2532991202%/Integrations/Hungry Europans/Content/Items/Food/FoodAndMeat.png" sourcerect="240,380,93,33" depth="0.6" origin="0.5,0.5" />
      <Body width="93" radius="16" density="12" />
      <AiTarget sightrange="1000" static="True" />
    </Item>
  </Override>
</Items>